INDEX/__init__.py
INDEX/demo.py
indexjpcjpc-1.0.1.dist-info/METADATA
indexjpcjpc-1.0.1.dist-info/RECORD
indexjpcjpc-1.0.1.dist-info/WHEEL
indexjpcjpc-1.0.1.dist-info/top_level.txt
